libname/__init__.py
libname/sayhello.py
dptest-0.0.2.dist-info/LICENSE
dptest-0.0.2.dist-info/METADATA
dptest-0.0.2.dist-info/WHEEL
dptest-0.0.2.dist-info/top_level.txt
dptest-0.0.2.dist-info/RECORD
