Metadata-Version: 2.1
Name: dptest
Version: 0.0.2
Summary: Basic hello
Author: My Name
Author-email: <pth.a15.33.tran.thien@gmail.com>
Keywords: python,test
Classifier: Development Status :: 1 - Planning
Classifier: Intended Audience :: Developers
Classifier: Programming Language :: Python :: 3
Classifier: Operating System :: Unix
Classifier: Operating System :: MacOS :: MacOS X
Classifier: Operating System :: Microsoft :: Windows
Classifier: License :: OSI Approved :: GNU General Public License v3 or later (GPLv3+)
License-File: LICENSE
Requires-Dist: numpy
